evHID/__init__.py
evHID/example.py
evHID/example2.py
evHID/focus
evHID/focus.c
evHID/pynput_refex.py
evHID/test_keyu.py
evHID/tester.py
evHID/tmpterm.py
evHID/Types/__init__.py
evHID/Types/callback.py
evHID/Types/coord.py
evHID/Types/data.py
evHID/Types/kb_key.py
evHID/Types/tempmod.py
evHID/Types/controls/__init__.py
evHID/dev/__init__.py
evHID/dev/gamepad.py
evHID/dev/keyboard.py
evHID/dev/midicontroller.py
evHID/dev/mouse.py
evHID/hid/__init__.py
evHID/hid/kbev.py
evHID/term/__init__.py
evHID/term/cursor.py
evHID/term/posix.py
evHID/term/types.py
evHID/term/winnt.py
evHID/tty/__init__.py
evHID/tty/posix.py
evhid-0.1.0.dist-info/METADATA
evhid-0.1.0.dist-info/WHEEL
evhid-0.1.0.dist-info/top_level.txt
evhid-0.1.0.dist-info/RECORD
