Metadata-Version: 2.4
Name: evhid
Version: 0.1.0
Summary: Python non-blocking terminal keyboard/mouse event detection for any presented to stdin
